py_spear-0.1.0.dist-info/METADATA
py_spear-0.1.0.dist-info/WHEEL
spear/__init__.py
spear/spear.cp310-win_amd64.pyd
py_spear-0.1.0.dist-info/RECORD
