Metadata-Version: 2.1
Name: py-spear
Version: 0.1.0
Classifier: Development Status :: 1 - Planning
Classifier: Topic :: Software Development :: Libraries :: Python Modules
Classifier: Programming Language :: Python :: Implementation :: CPython
Classifier: Programming Language :: Python :: Implementation :: PyPy
Classifier: Programming Language :: Python :: 3.7
Classifier: Programming Language :: Python :: 3.8
Classifier: Programming Language :: Python :: 3.9
Classifier: Programming Language :: Python :: 3.10
Classifier: Programming Language :: Rust
Summary: 🔱 Better, Faster dates & times for Python
Requires-Python: >=3.7
